funq_server/__init__.py
funq_server/libFunq.so
funq_server/runner.py
funq_server/runner_linux.py
funq_server/runner_mac.py
funq_server/runner_win.py
funq_server-1.2.0.dist-info/LICENCE-fr.txt
funq_server-1.2.0.dist-info/LICENCE.txt
funq_server-1.2.0.dist-info/METADATA
funq_server-1.2.0.dist-info/WHEEL
funq_server-1.2.0.dist-info/entry_points.txt
funq_server-1.2.0.dist-info/top_level.txt
funq_server-1.2.0.dist-info/RECORD
