Metadata-Version: 2.1
Name: funq-server
Version: 1.2.0
Summary: write FUNctional tests for Qt applications (server)
Home-page: https://github.com/parkouss/funq
Author: Julien Pagès
Author-email: j.parkouss@gmail.com
License: CeCILL v1.2
Platform: UNKNOWN
